owlsight/__init__.py
owlsight/main.py
owlsight/agentic/__init__.py
owlsight/agentic/constants.py
owlsight/agentic/core.py
owlsight/agentic/exceptions.py
owlsight/agentic/guardrails.py
owlsight/agentic/helper_functions.py
owlsight/agentic/models.py
owlsight/app/__init__.py
owlsight/app/_child_process_owl_press.py
owlsight/app/default_functions.py
owlsight/app/handlers.py
owlsight/app/run_app.py
owlsight/app/url_processor.py
owlsight/blobs/tika-server-standard-3.0.0-bin.zip
owlsight/blobs/tika-server-standard-3.0.0-bin.zip.md5
owlsight/configurations/__init__.py
owlsight/configurations/config_manager.py
owlsight/configurations/constants.py
owlsight/configurations/schema.py
owlsight/docs/helper_functions.py
owlsight/docs/readme.py
owlsight/docs/readme_content.py
owlsight/huggingface/__init__.py
owlsight/huggingface/constants.py
owlsight/huggingface/core.py
owlsight/huggingface/custom_classes.py
owlsight/huggingface/helper_functions.py
owlsight/huggingface/leaderboards.py
owlsight/multimodal/__init__.py
owlsight/multimodal/tesseract.py
owlsight/processors/__init__.py
owlsight/processors/base.py
owlsight/processors/constants.py
owlsight/processors/custom_classes.py
owlsight/processors/helper_functions.py
owlsight/processors/memory_context.py
owlsight/processors/multimodal_processors.py
owlsight/processors/text_generation_manager.py
owlsight/processors/text_generation_processors.py
owlsight/prompts/__init__.py
owlsight/prompts/helper_functions.py
owlsight/prompts/system_prompts.py
owlsight/rag/__init__.py
owlsight/rag/constants.py
owlsight/rag/core.py
owlsight/rag/custom_classes.py
owlsight/rag/document_reader.py
owlsight/rag/helper_functions.py
owlsight/rag/python_lib_search.py
owlsight/rag/text_splitters.py
owlsight/ui/__init__.py
owlsight/ui/console.py
owlsight/ui/constants.py
owlsight/ui/custom_classes.py
owlsight/ui/file_dialogs.py
owlsight/ui/logo.py
owlsight/utils/__init__.py
owlsight/utils/code_execution.py
owlsight/utils/constants.py
owlsight-2.6.1.dist-info/licenses/LICENSE
owlsight-2.6.1.dist-info/METADATA
owlsight-2.6.1.dist-info/WHEEL
owlsight-2.6.1.dist-info/entry_points.txt
owlsight-2.6.1.dist-info/top_level.txt
owlsight-2.6.1.dist-info/RECORD
