Metadata-Version: 2.4
Name: owlsight
Version: 2.6.1
Summary: Owlsight is a command-line tool combining open-source AI models with Python functionality to create a powerful AI assistant.
Author: Vincent Ouwendijk
License: MIT
Requires-Python: <3.13,>=3.9
License-File: LICENSE
Requires-Dist: psutil
Requires-Dist: transformers
Requires-Dist: pandas
Requires-Dist: numpy
Requires-Dist: torch
Requires-Dist: bitsandbytes; sys_platform == "linux" and platform_machine == "x86_64"
Requires-Dist: accelerate
Requires-Dist: sentencepiece
Requires-Dist: prompt_toolkit==2.0.10
Requires-Dist: scikit-learn
Requires-Dist: jinja2
Requires-Dist: tqdm
Requires-Dist: pynput
Requires-Dist: dill
Requires-Dist: tika
Provides-Extra: dev
Requires-Dist: build; extra == "dev"
Requires-Dist: twine; extra == "dev"
Requires-Dist: pytest; extra == "dev"
Requires-Dist: pytest-asyncio<=0.24; extra == "dev"
Requires-Dist: ruff; extra == "dev"
Requires-Dist: black; extra == "dev"
Requires-Dist: pylint; extra == "dev"
Provides-Extra: huggingface-metadata
Requires-Dist: gradio; extra == "huggingface-metadata"
Provides-Extra: gguf
Requires-Dist: llama-cpp-python; extra == "gguf"
Provides-Extra: onnx
Requires-Dist: onnxruntime-genai; extra == "onnx"
Requires-Dist: onnxruntime-genai-cuda; extra == "onnx"
Provides-Extra: search
Requires-Dist: lxml; extra == "search"
Requires-Dist: aiohttp; extra == "search"
Requires-Dist: duckduckgo_search; extra == "search"
Requires-Dist: sentence-transformers; extra == "search"
Provides-Extra: multimodal
Requires-Dist: pytesseract; extra == "multimodal"
Requires-Dist: pillow; extra == "multimodal"
Requires-Dist: beautifulsoup4; extra == "multimodal"
Provides-Extra: offline
Provides-Extra: voice
Requires-Dist: pyaudio; extra == "voice"
Requires-Dist: RealtimeSTT; extra == "voice"
Requires-Dist: ctranslate2==3.24.0; python_version < "3.13" and extra == "voice"
Provides-Extra: all
Requires-Dist: psutil; extra == "all"
Requires-Dist: transformers; extra == "all"
Requires-Dist: pandas; extra == "all"
Requires-Dist: numpy; extra == "all"
Requires-Dist: torch; extra == "all"
Requires-Dist: bitsandbytes; extra == "all"
Requires-Dist: accelerate; extra == "all"
Requires-Dist: sentencepiece; extra == "all"
Requires-Dist: prompt_toolkit<=2.0.10; extra == "all"
Requires-Dist: scikit-learn; extra == "all"
Requires-Dist: jinja2; extra == "all"
Requires-Dist: tqdm; extra == "all"
Requires-Dist: pynput; extra == "all"
Requires-Dist: tika; extra == "all"
Requires-Dist: lxml; extra == "all"
Requires-Dist: aiohttp; extra == "all"
Requires-Dist: duckduckgo_search; extra == "all"
Requires-Dist: llama-cpp-python; extra == "all"
Requires-Dist: onnxruntime-genai; extra == "all"
Requires-Dist: onnxruntime-genai-cuda; extra == "all"
Requires-Dist: sentence-transformers; extra == "all"
Requires-Dist: pytesseract; extra == "all"
Requires-Dist: beautifulsoup4; extra == "all"
Requires-Dist: pillow; extra == "all"
Dynamic: license-file
